Products.SAML2Plugins-0.9-py3.11-nspkg.pth
Products/SAML2Plugins/PluginBase.py
Products/SAML2Plugins/SAML2Plugin.py
Products/SAML2Plugins/__init__.py
Products/SAML2Plugins/configuration.py
Products/SAML2Plugins/configure.zcml
Products/SAML2Plugins/interfaces.py
Products/SAML2Plugins/metadata.py
Products/SAML2Plugins/monkeypatch.py
Products/SAML2Plugins/serviceprovider.py
Products/SAML2Plugins/browser/__init__.py
Products/SAML2Plugins/browser/assertionconsumer.py
Products/SAML2Plugins/browser/configure.zcml
Products/SAML2Plugins/browser/metadata.py
Products/SAML2Plugins/browser/tests/__init__.py
Products/SAML2Plugins/browser/tests/base.py
Products/SAML2Plugins/browser/tests/test_assertionconsumer.py
Products/SAML2Plugins/browser/tests/test_metadata.py
Products/SAML2Plugins/data/xenc-schema-11.xsd
Products/SAML2Plugins/tests/__init__.py
Products/SAML2Plugins/tests/base.py
Products/SAML2Plugins/tests/dummy.py
Products/SAML2Plugins/tests/test_SAML2Plugin.py
Products/SAML2Plugins/tests/test_configuration.py
Products/SAML2Plugins/tests/test_metadata.py
Products/SAML2Plugins/tests/test_serviceprovider.py
Products/SAML2Plugins/tests/test_data/dummy_local_idp_config.xml
Products/SAML2Plugins/tests/test_data/dummy_xmlsec1
Products/SAML2Plugins/tests/test_data/mocksaml_metadata.xml
Products/SAML2Plugins/tests/test_data/mocksaml_metadata_binding_post.xml
Products/SAML2Plugins/tests/test_data/saml2_cfg_invalid.py
Products/SAML2Plugins/tests/test_data/saml2_cfg_test1.py
Products/SAML2Plugins/tests/test_data/saml2_cfg_test2.py
Products/SAML2Plugins/tests/test_data/saml2_cfg_valid.py
Products/SAML2Plugins/tests/test_data/saml2plugintest.key
Products/SAML2Plugins/tests/test_data/saml2plugintest.pem
Products/SAML2Plugins/tests/test_data/samlresponse1.txt
Products/SAML2Plugins/www/SAML2Plugin_add.zpt
Products/SAML2Plugins/www/SAML2Plugin_config.zpt
Products/SAML2Plugins/www/SAML2Plugin_metadata.zpt
Products.SAML2Plugins-0.9.dist-info/LICENSE.txt
Products.SAML2Plugins-0.9.dist-info/METADATA
Products.SAML2Plugins-0.9.dist-info/WHEEL
Products.SAML2Plugins-0.9.dist-info/entry_points.txt
Products.SAML2Plugins-0.9.dist-info/namespace_packages.txt
Products.SAML2Plugins-0.9.dist-info/top_level.txt
Products.SAML2Plugins-0.9.dist-info/RECORD
