Metadata-Version: 2.1
Name: Products.SAML2Plugins
Version: 0.9
Summary: SAML 2.0 plugins for the Zope PluggableAuthService
Home-page: https://github.com/dataflake/Products.SAML2Plugins
Author: Jens Vagelpohl and contributors
Author-email: jens@dataflake.org
License: ZPL 2.1
Project-URL: Documentation, https://saml2plugins.readthedocs.io/
Project-URL: Issue Tracker, https://github.com/dataflake/Products.SAML2Plugins/issues
Project-URL: Sources, https://github.com/dataflake/Products.SAML2Plugins
Keywords: web application server zope saml saml2
Classifier: Development Status :: 4 - Beta
Classifier: Framework :: Zope
Classifier: Framework :: Zope :: 5
Classifier: Intended Audience :: Developers
Classifier: License :: OSI Approved :: Zope Public License
Classifier: Operating System :: OS Independent
Classifier: Programming Language :: Python :: 3
Classifier: Programming Language :: Python :: 3.7
Classifier: Programming Language :: Python :: 3.8
Classifier: Programming Language :: Python :: 3.9
Classifier: Programming Language :: Python :: 3.10
Classifier: Programming Language :: Python :: 3.11
Classifier: Programming Language :: Python :: 3.12
Classifier: Topic :: Internet :: WWW/HTTP :: Site Management
Classifier: Topic :: Software Development
Classifier: Topic :: System :: Systems Administration :: Authentication/Directory
Requires-Python: >=3.7
License-File: LICENSE.txt
Requires-Dist: setuptools
Requires-Dist: pysaml2
Requires-Dist: Zope >=5
Requires-Dist: Products.PluggableAuthService
Provides-Extra: docs
Requires-Dist: Sphinx ; extra == 'docs'
Requires-Dist: sphinx-rtd-theme ; extra == 'docs'
Requires-Dist: repoze.sphinx.autointerface ; extra == 'docs'
Requires-Dist: pkginfo ; extra == 'docs'
